flake8_safegraph_crawl/__init__.py
flake8_safegraph_crawl-0.4.dist-info/METADATA
flake8_safegraph_crawl-0.4.dist-info/WHEEL
flake8_safegraph_crawl-0.4.dist-info/entry_points.txt
flake8_safegraph_crawl-0.4.dist-info/top_level.txt
flake8_safegraph_crawl-0.4.dist-info/RECORD
