Metadata-Version: 2.1
Name: flake8-safegraph-crawl
Version: 0.4
Summary: Flake8 plugin enforcing code requirements for SafeGraph crawlers
Home-page: https://github.com/SafeGraphInc/flake8-safegraph-crawl
Author: UNKNOWN
Author-email: UNKNOWN
License: UNKNOWN
Platform: UNKNOWN
